<annotations><filename>2390.jpeg</filename><folder>images</folder><size><width>1280</width><height>720</height><depth>3</depth></size><object><name>drone</name><pose>Unspecified</pose><truncated>0</truncated><difficult>0</difficult><bndbox><xmin>579.0</xmin><ymin>65.00000000023199</ymin><xmax>623.0</xmax><ymax>94.000000000248</ymax></bndbox></object><object><name>drone</name><pose>Unspecified</pose><truncated>0</truncated><difficult>0</difficult><bndbox><xmin>746.0</xmin><ymin>330.999999999696</ymin><xmax>813.0</xmax><ymax>371.99999999966406</ymax></bndbox></object></annotations>